<Stats deaths="119" kills="21" player_kills="2" player_projectile_count="0" >
  <death_map>
    <E key="NULL | $damage_electricity" value="9" >
    </E>
    <E key="NULL | $damage_explosion" value="21" >
    </E>
    <E key="NULL | $damage_physicshit" value="9" >
    </E>
    <E key="NULL | damage from material: acid" value="2" >
    </E>
    <E key="NULL | damage from material: lava" value="1" >
    </E>
    <E key="broken_wand | $damage_slice" value="1" >
    </E>
    <E key="drone_lasership | $damage_projectile" value="3" >
    </E>
    <E key="plague_rats_rat | $damage_melee" value="1" >
    </E>
    <E key="player | $damage_electricity" value="4" >
    </E>
    <E key="player | $damage_explosion" value="34" >
    </E>
    <E key="player | $damage_projectile" value="13" >
    </E>
    <E key="player | $damage_slice" value="2" >
    </E>
    <E key="player_rng_items | $damage_explosion" value="11" >
    </E>
    <E key="player_rng_items | $damage_projectile" value="7" >
    </E>
    <E key="player_rng_items | $damage_slice" value="1" >
    </E>
  </death_map>
  <kill_map>
    <E key="bigzombie" value="1" >
    </E>
    <E key="bigzombietorso" value="1" >
    </E>
    <E key="chest_mimic" value="1" >
    </E>
    <E key="drone_lasership" value="2" >
    </E>
    <E key="miner" value="2" >
    </E>
    <E key="player" value="2" >
    </E>
    <E key="player_rng_items" value="2" >
    </E>
    <E key="scavenger_grenade" value="1" >
    </E>
    <E key="scavenger_heal" value="5" >
    </E>
    <E key="scavenger_smg" value="3" >
    </E>
    <E key="shaman" value="1" >
    </E>
  </kill_map>
</Stats>
