<Stats BUILD_NAME="Noita-Build-Apr 23 2021-18:44:24" >
  <stats biomes_visited_with_wands="10" damage_taken="23.9355" dead="1" death_count="0" death_pos.x="712.355" death_pos.y="9902.13" enemies_killed="210" gold="2645" gold_all="4905" gold_infinite="0" healed="0" heart_containers="0" hp="100" items="28" kicks="27" killed_by="Salamurhaajarobotti | melee" killed_by_extra="" places_visited="10" playtime="2511.67" playtime_str="0:41:51" projectiles_shot="4049" streaks="0" teleports="0" wands_edited="8" world_seed="285662457" >
  </stats>
  <biome_baseline biomes_visited_with_wands="9" damage_taken="17.3362" dead="0" death_count="0" death_pos.x="0" death_pos.y="0" enemies_killed="188" gold="1945" gold_all="4205" gold_infinite="0" healed="0" heart_containers="0" hp="100" items="28" kicks="26" killed_by="" killed_by_extra="" places_visited="9" playtime="2396.52" playtime_str="0:39:56" projectiles_shot="3696" streaks="0" teleports="0" wands_edited="8" world_seed="285662457" >
  </biome_baseline>
  <item_map>
  </item_map>
  <biomes_visited>
    <E key="$biome_coalmine" value="1" >
    </E>
    <E key="$biome_coalmine_alt" value="1" >
    </E>
    <E key="$biome_excavationsite" value="1" >
    </E>
    <E key="$biome_fungicave" value="1" >
    </E>
    <E key="$biome_holymountain" value="1" >
    </E>
    <E key="$biome_rainforest" value="1" >
    </E>
    <E key="$biome_snowcastle" value="1" >
    </E>
    <E key="$biome_snowcave" value="1" >
    </E>
    <E key="$biome_vault" value="1" >
    </E>
    <E key="$biome_wandcave" value="1" >
    </E>
  </biomes_visited>
</Stats>
