<Stats BUILD_NAME="Noita-Build-Dec  1 2020-15:56:41" >
  <stats biomes_visited_with_wands="3" damage_taken="8.67" dead="1" death_count="0" death_pos.x="-533.965" death_pos.y="5814.33" enemies_killed="28" gold="112" gold_all="452" gold_infinite="0" healed="0" heart_containers="0" hp="100" items="3" kicks="0" killed_by=" | explosion" killed_by_extra="" places_visited="3" playtime="119.017" playtime_str="0:01:59" projectiles_shot="166" teleports="0" wands_edited="1" world_seed="595287955" >
  </stats>
  <biome_baseline biomes_visited_with_wands="2" damage_taken="2.23" dead="0" death_count="0" death_pos.x="0" death_pos.y="0" enemies_killed="7" gold="22" gold_all="362" gold_infinite="0" healed="0" heart_containers="0" hp="100" items="3" kicks="0" killed_by="" killed_by_extra="" places_visited="2" playtime="72.8333" playtime_str="0:01:12" projectiles_shot="69" teleports="0" wands_edited="1" world_seed="595287955" >
  </biome_baseline>
  <item_map>
  </item_map>
  <biomes_visited>
    <E key="$biome_holymountain" value="1" >
    </E>
    <E key="$biome_snowcastle" value="1" >
    </E>
    <E key="$biome_snowcave" value="1" >
    </E>
  </biomes_visited>
</Stats>
